multilevellogger/__init__.py
multilevellogger/multilevelformatter.py
multilevellogger/multilevellogger.py
multilevellogger/py.typed
multilevellogger-0.7.1.dist-info/METADATA
multilevellogger-0.7.1.dist-info/WHEEL
multilevellogger-0.7.1.dist-info/licenses/LICENSE
multilevellogger-0.7.1.dist-info/RECORD
